hypdb/__init__.py
hypdb/core/MultipleTrreatmentTest.py
hypdb/core/__init__.py
hypdb/core/att_filtering.py
hypdb/core/cov_selection.py
hypdb/core/explanation.py
hypdb/core/matching.py
hypdb/core/query.py
hypdb/core/simdetec.py
hypdb/core/test.sql
hypdb/modules/infotheo/__init__.py
hypdb/modules/infotheo/info_theo.py
hypdb/modules/kbutil/LICENSE
hypdb/modules/kbutil/MANIFEST.in
hypdb/modules/kbutil/README
hypdb/modules/kbutil/__init__.py
hypdb/modules/kbutil/build/lib/kbutil/__init__.py
hypdb/modules/kbutil/build/lib/kbutil/listutil.py
hypdb/modules/kbutil/build/lib/kbutil/plotting.py
hypdb/modules/kbutil/build/lib/kbutil/rand.py
hypdb/modules/kbutil/build/lib/kbutil/statistics.py
hypdb/modules/kbutil/listutil.py
hypdb/modules/kbutil/plotting.py
hypdb/modules/kbutil/rand.py
hypdb/modules/kbutil/setup.py
hypdb/modules/kbutil/statistics.py
hypdb/modules/lpsolve_dev/liblpsolve55.a
hypdb/modules/lpsolve_dev/liblpsolve55.so
hypdb/modules/lpsolve_dev/lp_Hash.h
hypdb/modules/lpsolve_dev/lp_SOS.h
hypdb/modules/lpsolve_dev/lp_lib.h
hypdb/modules/lpsolve_dev/lp_matrix.h
hypdb/modules/lpsolve_dev/lp_mipbb.h
hypdb/modules/lpsolve_dev/lp_types.h
hypdb/modules/lpsolve_dev/lp_utils.h
hypdb/modules/pyrankagg/LICENSE
hypdb/modules/pyrankagg/MANIFEST.in
hypdb/modules/pyrankagg/README
hypdb/modules/pyrankagg/__init__.py
hypdb/modules/pyrankagg/agreement.py
hypdb/modules/pyrankagg/build/lib/pyrankagg/__init__.py
hypdb/modules/pyrankagg/build/lib/pyrankagg/agreement.py
hypdb/modules/pyrankagg/build/lib/pyrankagg/linear_assignment.py
hypdb/modules/pyrankagg/build/lib/pyrankagg/metrics.py
hypdb/modules/pyrankagg/build/lib/pyrankagg/rankagg.py
hypdb/modules/pyrankagg/build/lib/pyrankagg/tests/__init__.py
hypdb/modules/pyrankagg/build/lib/pyrankagg/tests/runtests.py
hypdb/modules/pyrankagg/build/lib/pyrankagg/tests/test_aggregation.py
hypdb/modules/pyrankagg/build/lib/pyrankagg/tests/test_metrics.py
hypdb/modules/pyrankagg/kbutil/LICENSE
hypdb/modules/pyrankagg/kbutil/MANIFEST.in
hypdb-1.0.0.dist-info/WHEEL
hypdb-1.0.0.dist-info/METADATA
hypdb-1.0.0.dist-info/RECORD
